jetimage_processor/__init__.py
jetimage_processor/config.py
jetimage_processor/default_config.yaml
jetimage_processor/processor.py
jetimage_processor/transform_helper.py
jetimage_processor-0.1.0.dist-info/LICENSE
jetimage_processor-0.1.0.dist-info/METADATA
jetimage_processor-0.1.0.dist-info/WHEEL
jetimage_processor-0.1.0.dist-info/entry_points.txt
jetimage_processor-0.1.0.dist-info/top_level.txt
jetimage_processor-0.1.0.dist-info/RECORD
