Metadata-Version: 2.1
Name: jetimage-processor
Version: 0.1.0
Summary: A tool for processing jet images from ROOT files
Author: Fabrizio Napolitano
License: MIT
Keywords: jet images,ROOT,high-energy physics,jet substructure,machine learning
Classifier: Programming Language :: Python :: 3
Classifier: License :: OSI Approved :: MIT License
Classifier: Operating System :: OS Independent
Requires-Python: >=3.11
License-File: LICENSE
Requires-Dist: numpy
Requires-Dist: matplotlib
Requires-Dist: uproot
Requires-Dist: h5py
Requires-Dist: scipy
Requires-Dist: PyYAML
Requires-Dist: pyarrow
Requires-Dist: pandas
